{
  "group_name": "Core",
  "description": "Core stability and anti-movement exercises",
  "last_updated": "2026-02-02T13:09:53.585679Z",
  "exercise_count": {
    "main": 12,
    "warmup": 7,
    "cooldown": 0,
    "total": 19
  },
  "main_exercises": [
    {
      "exercise_id": "ex_0120",
      "exercise_name": "Dead Bug",
      "category": "core",
      "body_region": "core",
      "movement_pattern": "anti_extension",
      "equipment": "bodyweight",
      "primary_muscles": "rectus_abdominis,deep_core",
      "segment_type": "main; warmup",
      "difficulty": "intermediate",
      "coaching_cues_short": "Ribs down",
      "safety_notes": "Avoid lumbar arching.",
      "regression": "Dead Bug (Arms Only)",
      "progression": "Band-Resisted Dead Bug",
      "training_focus": "power,coordination",
      "secondary_muscles": "hip_flexors,shoulders",
      "special_flags": "joint_friendly"
    },
    {
      "exercise_id": "ex_0121",
      "exercise_name": "Plank",
      "category": "core",
      "body_region": "core",
      "movement_pattern": "anti_extension",
      "equipment": "bodyweight",
      "primary_muscles": "rectus_abdominis,transverse_abdominis",
      "segment_type": "main; warmup",
      "difficulty": "intermediate",
      "coaching_cues_short": "Brace and breathe",
      "safety_notes": "Avoid sagging hips.",
      "regression": "Knee Plank",
      "progression": "RKC Plank",
      "training_focus": "power,coordination",
      "secondary_muscles": "hip_flexors,shoulders",
      "special_flags": "joint_friendly"
    },
    {
      "exercise_id": "ex_0122",
      "exercise_name": "Side Plank",
      "category": "core",
      "body_region": "core",
      "movement_pattern": "anti_lateral_flexion",
      "equipment": "bodyweight",
      "primary_muscles": "obliques,glute_medius",
      "segment_type": "main; warmup",
      "difficulty": "intermediate",
      "coaching_cues_short": "Hips stacked",
      "safety_notes": "Avoid shoulder shrugging.",
      "regression": "Bent-Knee Side Plank",
      "progression": "Side Plank with Hip Abduction",
      "training_focus": "strength,power",
      "secondary_muscles": "shoulders,hip_flexors",
      "special_flags": "spine_loaded"
    },
    {
      "exercise_id": "ex_0123",
      "exercise_name": "Bird Dog",
      "category": "core",
      "body_region": "core",
      "movement_pattern": "anti_rotation",
      "equipment": "bodyweight",
      "primary_muscles": "erectors,deep_core",
      "segment_type": "main; warmup",
      "difficulty": "intermediate",
      "coaching_cues_short": "Reach long",
      "safety_notes": "Avoid shifting hips.",
      "regression": "Bird Dog Hold",
      "progression": "Band-Resisted Bird Dog",
      "training_focus": "coordination,power",
      "secondary_muscles": "shoulders,hip_flexors",
      "special_flags": "joint_friendly"
    },
    {
      "exercise_id": "ex_0124",
      "exercise_name": "Hollow Body Hold",
      "category": "core",
      "body_region": "core",
      "movement_pattern": "anti_extension",
      "equipment": "bodyweight",
      "primary_muscles": "rectus_abdominis",
      "segment_type": "main; warmup",
      "difficulty": "advanced",
      "coaching_cues_short": "Lower back down",
      "safety_notes": "Exit if back arches.",
      "regression": "Tuck Hold",
      "progression": "Hollow Rocks",
      "training_focus": "stability,strength",
      "secondary_muscles": "shoulders,hip_flexors",
      "special_flags": "shoulder_intensive"
    },
    {
      "exercise_id": "ex_0125",
      "exercise_name": "Pallof Press",
      "category": "core",
      "body_region": "core",
      "movement_pattern": "anti_rotation",
      "equipment": "cable_system",
      "primary_muscles": "obliques,deep_core",
      "segment_type": "main; warmup",
      "difficulty": "beginner",
      "coaching_cues_short": "Resist rotation",
      "safety_notes": "Use light resistance.",
      "regression": "Half-Kneeling Pallof Press",
      "progression": "Rotational Press",
      "training_focus": "endurance,aerobic",
      "special_flags": "low_impact,joint_friendly"
    },
    {
      "exercise_id": "ex_0126",
      "exercise_name": "Cable Chop",
      "category": "core",
      "body_region": "core",
      "movement_pattern": "rotation",
      "equipment": "cable_system",
      "primary_muscles": "obliques",
      "segment_type": "main; warmup",
      "difficulty": "beginner",
      "coaching_cues_short": "Rotate under control",
      "safety_notes": "Control range.",
      "regression": "Pallof Press",
      "progression": "Cable Lift",
      "training_focus": "aerobic,endurance",
      "special_flags": "low_impact"
    },
    {
      "exercise_id": "ex_0127",
      "exercise_name": "Cable Lift",
      "category": "core",
      "body_region": "core",
      "movement_pattern": "rotation",
      "equipment": "cable_system",
      "primary_muscles": "obliques",
      "segment_type": "main; warmup",
      "difficulty": "intermediate",
      "coaching_cues_short": "Drive from hips",
      "safety_notes": "Stable base required.",
      "regression": "Pallof Press",
      "progression": "Rotational Throw",
      "training_focus": "aerobic,speed"
    },
    {
      "exercise_id": "ex_0128",
      "exercise_name": "Farmer Carry",
      "category": "core",
      "body_region": "full",
      "movement_pattern": "anti_lateral_flexion",
      "equipment": "free_weight",
      "primary_muscles": "core,forearms,glutes",
      "segment_type": "main; warmup",
      "difficulty": "intermediate",
      "coaching_cues_short": "Tall posture",
      "safety_notes": "Grip must be secure.",
      "regression": "Suitcase Carry",
      "progression": "Heavy Farmer Carry",
      "training_focus": "anaerobic,speed",
      "secondary_muscles": "core"
    },
    {
      "exercise_id": "ex_0129",
      "exercise_name": "Suitcase Carry",
      "category": "core",
      "body_region": "full",
      "movement_pattern": "anti_lateral_flexion",
      "equipment": "free_weight",
      "primary_muscles": "obliques,core",
      "segment_type": "main; warmup",
      "difficulty": "intermediate",
      "coaching_cues_short": "Stay upright",
      "safety_notes": "Progress load slowly.",
      "regression": "Farmer Carry",
      "progression": "Offset Carry",
      "training_focus": "power,endurance",
      "secondary_muscles": "glutes,core"
    },
    {
      "exercise_id": "ex_0130",
      "exercise_name": "Ab Wheel Rollout",
      "category": "core",
      "body_region": "core",
      "movement_pattern": "anti_extension",
      "equipment": "portable_accessory",
      "primary_muscles": "rectus_abdominis",
      "segment_type": "main; warmup",
      "difficulty": "beginner",
      "coaching_cues_short": "Brace hard",
      "safety_notes": "Start from knees.",
      "regression": "Plank",
      "progression": "Standing Rollout",
      "training_focus": "aerobic,endurance",
      "special_flags": "low_impact,joint_friendly"
    },
    {
      "exercise_id": "ex_0131",
      "exercise_name": "Isometric Carry Hold",
      "category": "core",
      "body_region": "full",
      "movement_pattern": "anti_lateral_flexion",
      "equipment": "free_weight",
      "primary_muscles": "core,forearms",
      "segment_type": "main; warmup",
      "difficulty": "beginner",
      "coaching_cues_short": "Hold tall",
      "safety_notes": "Avoid breath holding.",
      "regression": "Light Carry",
      "progression": "Farmer Carry",
      "training_focus": "aerobic,endurance",
      "secondary_muscles": "core",
      "special_flags": "low_impact,joint_friendly"
    }
  ],
  "warmup_exercises": [
    {
      "exercise_id": "ex_0120",
      "exercise_name": "Dead Bug",
      "category": "core",
      "body_region": "core",
      "movement_pattern": "anti_extension",
      "equipment": "bodyweight",
      "primary_muscles": "rectus_abdominis,deep_core",
      "segment_type": "main; warmup",
      "difficulty": "intermediate",
      "coaching_cues_short": "Ribs down",
      "safety_notes": "Avoid lumbar arching.",
      "regression": "Dead Bug (Arms Only)",
      "progression": "Band-Resisted Dead Bug",
      "training_focus": "power,coordination",
      "secondary_muscles": "hip_flexors,shoulders",
      "special_flags": "joint_friendly"
    },
    {
      "exercise_id": "ex_0121",
      "exercise_name": "Plank",
      "category": "core",
      "body_region": "core",
      "movement_pattern": "anti_extension",
      "equipment": "bodyweight",
      "primary_muscles": "rectus_abdominis,transverse_abdominis",
      "segment_type": "main; warmup",
      "difficulty": "intermediate",
      "coaching_cues_short": "Brace and breathe",
      "safety_notes": "Avoid sagging hips.",
      "regression": "Knee Plank",
      "progression": "RKC Plank",
      "training_focus": "power,coordination",
      "secondary_muscles": "hip_flexors,shoulders",
      "special_flags": "joint_friendly"
    },
    {
      "exercise_id": "ex_0122",
      "exercise_name": "Side Plank",
      "category": "core",
      "body_region": "core",
      "movement_pattern": "anti_lateral_flexion",
      "equipment": "bodyweight",
      "primary_muscles": "obliques,glute_medius",
      "segment_type": "main; warmup",
      "difficulty": "intermediate",
      "coaching_cues_short": "Hips stacked",
      "safety_notes": "Avoid shoulder shrugging.",
      "regression": "Bent-Knee Side Plank",
      "progression": "Side Plank with Hip Abduction",
      "training_focus": "strength,power",
      "secondary_muscles": "shoulders,hip_flexors",
      "special_flags": "spine_loaded"
    },
    {
      "exercise_id": "ex_0123",
      "exercise_name": "Bird Dog",
      "category": "core",
      "body_region": "core",
      "movement_pattern": "anti_rotation",
      "equipment": "bodyweight",
      "primary_muscles": "erectors,deep_core",
      "segment_type": "main; warmup",
      "difficulty": "intermediate",
      "coaching_cues_short": "Reach long",
      "safety_notes": "Avoid shifting hips.",
      "regression": "Bird Dog Hold",
      "progression": "Band-Resisted Bird Dog",
      "training_focus": "coordination,power",
      "secondary_muscles": "shoulders,hip_flexors",
      "special_flags": "joint_friendly"
    },
    {
      "exercise_id": "ex_0124",
      "exercise_name": "Hollow Body Hold",
      "category": "core",
      "body_region": "core",
      "movement_pattern": "anti_extension",
      "equipment": "bodyweight",
      "primary_muscles": "rectus_abdominis",
      "segment_type": "main; warmup",
      "difficulty": "advanced",
      "coaching_cues_short": "Lower back down",
      "safety_notes": "Exit if back arches.",
      "regression": "Tuck Hold",
      "progression": "Hollow Rocks",
      "training_focus": "stability,strength",
      "secondary_muscles": "shoulders,hip_flexors",
      "special_flags": "shoulder_intensive"
    },
    {
      "exercise_id": "ex_0125",
      "exercise_name": "Pallof Press",
      "category": "core",
      "body_region": "core",
      "movement_pattern": "anti_rotation",
      "equipment": "cable_system",
      "primary_muscles": "obliques,deep_core",
      "segment_type": "main; warmup",
      "difficulty": "beginner",
      "coaching_cues_short": "Resist rotation",
      "safety_notes": "Use light resistance.",
      "regression": "Half-Kneeling Pallof Press",
      "progression": "Rotational Press",
      "training_focus": "endurance,aerobic",
      "special_flags": "low_impact,joint_friendly"
    },
    {
      "exercise_id": "ex_0130",
      "exercise_name": "Ab Wheel Rollout",
      "category": "core",
      "body_region": "core",
      "movement_pattern": "anti_extension",
      "equipment": "portable_accessory",
      "primary_muscles": "rectus_abdominis",
      "segment_type": "main; warmup",
      "difficulty": "beginner",
      "coaching_cues_short": "Brace hard",
      "safety_notes": "Start from knees.",
      "regression": "Plank",
      "progression": "Standing Rollout",
      "training_focus": "aerobic,endurance",
      "special_flags": "low_impact,joint_friendly"
    }
  ],
  "cooldown_exercises": []
}